micropdf/__init__.py
micropdf/buffer.py
micropdf/colorspace.py
micropdf/context.py
micropdf/document.py
micropdf/easy.py
micropdf/enhanced.py
micropdf/errors.py
micropdf/ffi.py
micropdf/ffi_full.py
micropdf/geometry.py
micropdf/geometry_fast.py
micropdf/native.py
micropdf/pixmap.py
micropdf/profiler.py
micropdf/py.typed
micropdf/resource_tracking.py
micropdf/version.py
micropdf-0.6.0.dist-info/licenses/LICENSE
micropdf-0.6.0.dist-info/METADATA
micropdf-0.6.0.dist-info/WHEEL
micropdf-0.6.0.dist-info/top_level.txt
micropdf-0.6.0.dist-info/RECORD
