Metadata-Version: 2.4
Name: micropdf
Version: 0.6.0
Summary: Python bindings for MicroPDF - High-performance PDF manipulation library
Author-email: Lexmata <info@lexmata.ai>
License-Expression: Apache-2.0
Project-URL: Homepage, https://bitbucket.org/lexmata/micropdf
Project-URL: Documentation, https://bitbucket.org/lexmata/micropdf
Project-URL: Repository, https://bitbucket.org/lexmata/micropdf
Project-URL: Bug Tracker, https://bitbucket.org/lexmata/micropdf/issues
Keywords: pdf,micropdf,document,parser,native,rust
Classifier: Development Status :: 4 - Beta
Classifier: Intended Audience :: Developers
Classifier: Programming Language :: Python :: 3
Classifier: Programming Language :: Python :: 3.8
Classifier: Programming Language :: Python :: 3.9
Classifier: Programming Language :: Python :: 3.10
Classifier: Programming Language :: Python :: 3.11
Classifier: Programming Language :: Python :: 3.12
Classifier: Programming Language :: Rust
Classifier: Topic :: Software Development :: Libraries
Classifier: Topic :: Text Processing
Classifier: Operating System :: OS Independent
Requires-Python: >=3.8
License-File: LICENSE
Requires-Dist: cffi>=1.16.0
Provides-Extra: dev
Requires-Dist: pytest>=7.4.0; extra == "dev"
Requires-Dist: pytest-cov>=4.1.0; extra == "dev"
Requires-Dist: black>=23.0.0; extra == "dev"
Requires-Dist: mypy>=1.5.0; extra == "dev"
Requires-Dist: ruff>=0.1.0; extra == "dev"
Requires-Dist: sphinx>=7.0.0; extra == "dev"
Requires-Dist: sphinx-rtd-theme>=1.3.0; extra == "dev"
Provides-Extra: docs
Requires-Dist: sphinx>=7.0.0; extra == "docs"
Requires-Dist: sphinx-rtd-theme>=1.3.0; extra == "docs"
Dynamic: license-file
